nova/virt/dpm/__init__.py
nova/virt/dpm/driver.py
nova_dpm/__init__.py
nova_dpm/version.py
nova_dpm/conf/__init__.py
nova_dpm/conf/cfg.py
nova_dpm/conf/dpm.py
nova_dpm/conf/types.py
nova_dpm/tests/__init__.py
nova_dpm/tests/unit/__init__.py
nova_dpm/tests/unit/conf/__init__.py
nova_dpm/tests/unit/conf/test_cfg.py
nova_dpm/tests/unit/conf/test_dpm.py
nova_dpm/tests/unit/conf/test_types.py
nova_dpm/tests/unit/guest_image_tools/__init__.py
nova_dpm/tests/unit/guest_image_tools/test_dpm_guest_image_tools.py
nova_dpm/tests/unit/guest_image_tools/test_wrapper.sh
nova_dpm/tests/unit/guest_image_tools/root_dir_default/znetconf
nova_dpm/tests/unit/guest_image_tools/root_dir_default/proc/cmdline
nova_dpm/tests/unit/guest_image_tools/root_dir_default/sbin/ip
nova_dpm/tests/unit/guest_image_tools/root_dir_default/sys/bus/ccwgroup/devices/0.0.0001/.placeholder
nova_dpm/tests/unit/guest_image_tools/root_dir_modprobe/modprobe
nova_dpm/tests/unit/virt/__init__.py
nova_dpm/tests/unit/virt/dpm/__init__.py
nova_dpm/tests/unit/virt/dpm/test_block_device.py
nova_dpm/tests/unit/virt/dpm/test_data.py
nova_dpm/tests/unit/virt/dpm/test_driver.py
nova_dpm/tests/unit/virt/dpm/test_host.py
nova_dpm/tests/unit/virt/dpm/test_utils.py
nova_dpm/tests/unit/virt/dpm/test_vif.py
nova_dpm/tests/unit/virt/dpm/test_vm.py
nova_dpm/virt/__init__.py
nova_dpm/virt/dpm/__init__.py
nova_dpm/virt/dpm/block_device.py
nova_dpm/virt/dpm/client_proxy.py
nova_dpm/virt/dpm/constants.py
nova_dpm/virt/dpm/driver.py
nova_dpm/virt/dpm/exceptions.py
nova_dpm/virt/dpm/host.py
nova_dpm/virt/dpm/utils.py
nova_dpm/virt/dpm/vif.py
nova_dpm/virt/dpm/vm.py
nova_dpm/virt/dpm/volume/__init__.py
nova_dpm/virt/dpm/volume/fibrechannel.py
nova_dpm/virt/dpm/volume/volume.py
nova_dpm-3.0.0.dist-info/DESCRIPTION.rst
nova_dpm-3.0.0.dist-info/METADATA
nova_dpm-3.0.0.dist-info/RECORD
nova_dpm-3.0.0.dist-info/WHEEL
nova_dpm-3.0.0.dist-info/entry_points.txt
nova_dpm-3.0.0.dist-info/metadata.json
nova_dpm-3.0.0.dist-info/pbr.json
nova_dpm-3.0.0.dist-info/top_level.txt
